<?xml version="1.0"?>
<phpunit xmlns="https://schema.phpunit.de/coverage/1.0">
  <file name="SmartHandlerInterface.php" path="/Handler">
    <totals>
      <lines total="13" comments="0" code="13" executable="0" executed="0" percent="0"/>
      <methods count="0" tested="0" percent="0"/>
      <functions count="0" tested="0" percent="0"/>
      <classes count="0" tested="0" percent="0"/>
      <traits count="0" tested="0" percent="0"/>
    </totals>
    <source>
      <line no="1">
        <token name="T_OPEN_TAG">&lt;?php</token>
      </line>
      <line no="2"/>
      <line no="3">
        <token name="T_DECLARE">declare</token>
        <token name="T_OPEN_BRACKET">(</token>
        <token name="T_STRING">strict_types</token>
        <token name="T_WHITESPACE"> </token>
        <token name="T_EQUAL">=</token>
        <token name="T_WHITESPACE"> </token>
        <token name="T_LNUMBER">1</token>
        <token name="T_CLOSE_BRACKET">)</token>
        <token name="T_SEMICOLON">;</token>
      </line>
      <line no="4"/>
      <line no="5">
        <token name="T_NAMESPACE">namespace</token>
        <token name="T_WHITESPACE"> </token>
        <token name="T_NAME_QUALIFIED">myrpc\Handler</token>
        <token name="T_SEMICOLON">;</token>
      </line>
      <line no="6"/>
      <line no="7">
        <token name="T_USE">use</token>
        <token name="T_WHITESPACE"> </token>
        <token name="T_NAME_QUALIFIED">myrpc\Handler\Context\ContextInterface</token>
        <token name="T_SEMICOLON">;</token>
      </line>
      <line no="8"/>
      <line no="9">
        <token name="T_INTERFACE">interface</token>
        <token name="T_WHITESPACE"> </token>
        <token name="T_STRING">SmartHandlerInterface</token>
        <token name="T_WHITESPACE"> </token>
        <token name="T_EXTENDS">extends</token>
        <token name="T_WHITESPACE"> </token>
        <token name="T_STRING">HandlerWithSchemaInterface</token>
      </line>
      <line no="10">
        <token name="T_OPEN_CURLY">{</token>
      </line>
      <line no="11">
        <token name="T_WHITESPACE">    </token>
        <token name="T_PUBLIC">public</token>
        <token name="T_WHITESPACE"> </token>
        <token name="T_FUNCTION">function</token>
        <token name="T_WHITESPACE"> </token>
        <token name="T_STRING">setContext</token>
        <token name="T_OPEN_BRACKET">(</token>
        <token name="T_STRING">ContextInterface</token>
        <token name="T_WHITESPACE"> </token>
        <token name="T_VARIABLE">$context</token>
        <token name="T_CLOSE_BRACKET">)</token>
        <token name="T_COLON">:</token>
        <token name="T_WHITESPACE"> </token>
        <token name="T_STRING">void</token>
        <token name="T_SEMICOLON">;</token>
      </line>
      <line no="12">
        <token name="T_CLOSE_CURLY">}</token>
      </line>
      <line no="13"/>
    </source>
  </file>
</phpunit>
